[
  {
    "id": "T00001",
    "ticker": "HELI.CA",
    "company_name": "Heliopolis Housing",
    "arabic_name": "ูุตุฑ ุงูุฌุฏูุฏุฉ ููุฅุณูุงู",
    "direction": "BUY",
    "entry_price": 3.57,
    "current_price": 3.57,
    "stop_loss": 3.39,
    "take_profit": 3.93,
    "quantity": 280,
    "investment_amount": 999.6,
    "entry_time": "2026-02-08T00:41:14.199965",
    "exit_time": null,
    "exit_price": null,
    "status": "ููุชูุญุฉ",
    "pnl": 0.0,
    "pnl_percent": 0.0,
    "signal_confidence": 100.0,
    "reasons": [
      "๐ MACD ูุนุทู ุฅุดุงุฑุฉ ุตุงุนุฏุฉ",
      "๐ ุงูููุณุชูุฌุฑุงู ููุฌุจ - ุชุฃููุฏ ููุงุชุฌุงู ุงูุตุงุนุฏ",
      "๐ ุงูุณุนุฑ ููู ุงููุชูุณุทุงุช ุงููุชุญุฑูุฉ 20 ู 50"
    ]
  },
  {
    "id": "T00002",
    "ticker": "HDBK.CA",
    "company_name": "Housing & Development Bank",
    "arabic_name": "ุจูู ุงูุชุนููุฑ ูุงูุฅุณูุงู",
    "direction": "BUY",
    "entry_price": 97.01,
    "current_price": 97.01,
    "stop_loss": 92.16,
    "take_profit": 106.71,
    "quantity": 10,
    "investment_amount": 970.1,
    "entry_time": "2026-02-08T00:41:14.205646",
    "exit_time": null,
    "exit_price": null,
    "status": "ููุชูุญุฉ",
    "pnl": 0.0,
    "pnl_percent": 0.0,
    "signal_confidence": 83.3,
    "reasons": [
      "๐ RSI (58.9) ูููู ููุงุฑุชูุงุน",
      "๐ MACD ูุนุทู ุฅุดุงุฑุฉ ุตุงุนุฏุฉ",
      "๐ ุงูููุณุชูุฌุฑุงู ููุฌุจ - ุชุฃููุฏ ููุงุชุฌุงู ุงูุตุงุนุฏ",
      "๐ ุงููุชูุณุทุงุช ุงููุชุญุฑูุฉ ุชุดูุฑ ูุงุชุฌุงู ุตุงุนุฏ ููู",
      "๐ ุงูุณุนุฑ ููู ุงููุชูุณุทุงุช ุงููุชุญุฑูุฉ 20 ู 50"
    ]
  },
  {
    "id": "T00003",
    "ticker": "EXPA.CA",
    "company_name": "Export Development Bank",
    "arabic_name": "ุงูุจูู ุงููุตุฑู ูุชูููุฉ ุงูุตุงุฏุฑุงุช",
    "direction": "BUY",
    "entry_price": 16.39,
    "current_price": 16.39,
    "stop_loss": 15.57,
    "take_profit": 18.03,
    "quantity": 61,
    "investment_amount": 999.79,
    "entry_time": "2026-02-08T00:41:14.217977",
    "exit_time": null,
    "exit_price": null,
    "status": "ููุชูุญุฉ",
    "pnl": 0.0,
    "pnl_percent": 0.0,
    "signal_confidence": 83.3,
    "reasons": [
      "๐ RSI (61.0) ูููู ููุงุฑุชูุงุน",
      "๐ MACD ูุนุทู ุฅุดุงุฑุฉ ุตุงุนุฏุฉ",
      "๐ ุงูููุณุชูุฌุฑุงู ููุฌุจ - ุชุฃููุฏ ููุงุชุฌุงู ุงูุตุงุนุฏ",
      "๐ ุงููุชูุณุทุงุช ุงููุชุญุฑูุฉ ุชุดูุฑ ูุงุชุฌุงู ุตุงุนุฏ ููู",
      "๐ ุงูุณุนุฑ ููู ุงููุชูุณุทุงุช ุงููุชุญุฑูุฉ 20 ู 50"
    ]
  },
  {
    "id": "T00004",
    "ticker": "TMGH.CA",
    "company_name": "Talaat Moustafa Group",
    "arabic_name": "ุทูุนุช ูุตุทูู ุงููุงุจุถุฉ",
    "direction": "BUY",
    "entry_price": 88.02,
    "current_price": 88.02,
    "stop_loss": 83.62,
    "take_profit": 96.82,
    "quantity": 11,
    "investment_amount": 968.22,
    "entry_time": "2026-02-08T00:55:01.898799",
    "exit_time": null,
    "exit_price": null,
    "status": "ููุชูุญุฉ",
    "pnl": 0.0,
    "pnl_percent": 0.0,
    "signal_confidence": 83.3,
    "reasons": [
      "๐ RSI (67.0) ูููู ููุงุฑุชูุงุน",
      "๐ MACD ูุนุทู ุฅุดุงุฑุฉ ุตุงุนุฏุฉ",
      "๐ ุงูููุณุชูุฌุฑุงู ููุฌุจ - ุชุฃููุฏ ููุงุชุฌุงู ุงูุตุงุนุฏ",
      "๐ ุงููุชูุณุทุงุช ุงููุชุญุฑูุฉ ุชุดูุฑ ูุงุชุฌุงู ุตุงุนุฏ ููู",
      "๐ ุงูุณุนุฑ ููู ุงููุชูุณุทุงุช ุงููุชุญุฑูุฉ 20 ู 50"
    ]
  },
  {
    "id": "T00005",
    "ticker": "PHDC.CA",
    "company_name": "Palm Hills Development",
    "arabic_name": "ุจุงูู ูููุฒ ููุชุนููุฑ",
    "direction": "BUY",
    "entry_price": 8.83,
    "current_price": 8.83,
    "stop_loss": 8.39,
    "take_profit": 9.71,
    "quantity": 113,
    "investment_amount": 997.79,
    "entry_time": "2026-02-08T00:55:01.904363",
    "exit_time": null,
    "exit_price": null,
    "status": "ููุชูุญุฉ",
    "pnl": 0.0,
    "pnl_percent": 0.0,
    "signal_confidence": 83.3,
    "reasons": [
      "๐ RSI (55.7) ูููู ููุงุฑุชูุงุน",
      "๐ MACD ูุนุทู ุฅุดุงุฑุฉ ุตุงุนุฏุฉ",
      "๐ ุงูููุณุชูุฌุฑุงู ููุฌุจ - ุชุฃููุฏ ููุงุชุฌุงู ุงูุตุงุนุฏ",
      "๐ ุงููุชูุณุทุงุช ุงููุชุญุฑูุฉ ุชุดูุฑ ูุงุชุฌุงู ุตุงุนุฏ ููู",
      "๐ ุงูุณุนุฑ ููู ุงููุชูุณุทุงุช ุงููุชุญุฑูุฉ 20 ู 50"
    ]
  },
  {
    "id": "T00006",
    "ticker": "COMI.CA",
    "company_name": "Commercial International Bank (CIB)",
    "arabic_name": "ุงูุจูู ุงูุชุฌุงุฑู ุงูุฏููู",
    "direction": "BUY",
    "entry_price": 137.25,
    "current_price": 137.25,
    "stop_loss": 130.39,
    "take_profit": 150.98,
    "quantity": 7,
    "investment_amount": 960.75,
    "entry_time": "2026-02-08T00:55:01.909368",
    "exit_time": null,
    "exit_price": null,
    "status": "ููุชูุญุฉ",
    "pnl": 0.0,
    "pnl_percent": 0.0,
    "signal_confidence": 76.5,
    "reasons": [
      "๐ RSI (75.9) ูู ููุทูุฉ ุฐุฑูุฉ ุงูุดุฑุงุก - ูุฑุตุฉ ุจูุน",
      "๐ MACD ูุนุทู ุฅุดุงุฑุฉ ุตุงุนุฏุฉ",
      "๐ ุงูููุณุชูุฌุฑุงู ููุฌุจ - ุชุฃููุฏ ููุงุชุฌุงู ุงูุตุงุนุฏ",
      "๐ ุงููุชูุณุทุงุช ุงููุชุญุฑูุฉ ุชุดูุฑ ูุงุชุฌุงู ุตุงุนุฏ ููู",
      "๐ ุงูุณุนุฑ ููู ุงููุชูุณุทุงุช ุงููุชุญุฑูุฉ 20 ู 50",
      "๐ ุญุฌู ุชุฏุงูู ูุฑุชูุน (2.0x) - ุชุฃููุฏ ููุดุฑุงุก"
    ]
  },
  {
    "id": "T00007",
    "ticker": "ADIB.CA",
    "company_name": "Abu Dhabi Islamic Bank Egypt",
    "arabic_name": "ูุตุฑู ุฃุจูุธุจู ุงูุฅุณูุงูู ูุตุฑ",
    "direction": "BUY",
    "entry_price": 39.0,
    "current_price": 39.0,
    "stop_loss": 37.05,
    "take_profit": 42.9,
    "quantity": 25,
    "investment_amount": 975.0,
    "entry_time": "2026-02-08T00:55:01.939415",
    "exit_time": null,
    "exit_price": null,
    "status": "ููุชูุญุฉ",
    "pnl": 0.0,
    "pnl_percent": 0.0,
    "signal_confidence": 71.4,
    "reasons": [
      "๐ RSI (75.2) ูู ููุทูุฉ ุฐุฑูุฉ ุงูุดุฑุงุก - ูุฑุตุฉ ุจูุน",
      "๐ MACD ูุนุทู ุฅุดุงุฑุฉ ุตุงุนุฏุฉ",
      "๐ ุงูููุณุชูุฌุฑุงู ููุฌุจ - ุชุฃููุฏ ููุงุชุฌุงู ุงูุตุงุนุฏ",
      "๐ ุงููุชูุณุทุงุช ุงููุชุญุฑูุฉ ุชุดูุฑ ูุงุชุฌุงู ุตุงุนุฏ ููู",
      "๐ ุงูุณุนุฑ ููู ุงููุชูุณุทุงุช ุงููุชุญุฑูุฉ 20 ู 50"
    ]
  },
  {
    "id": "T00008",
    "ticker": "EFIH.CA",
    "company_name": "E-Finance",
    "arabic_name": "ุฅู ูุงููุงูุณ",
    "direction": "BUY",
    "entry_price": 22.9,
    "current_price": 22.9,
    "stop_loss": 21.76,
    "take_profit": 25.19,
    "quantity": 43,
    "investment_amount": 984.7,
    "entry_time": "2026-02-08T00:55:01.982793",
    "exit_time": null,
    "exit_price": null,
    "status": "ููุชูุญุฉ",
    "pnl": 0.0,
    "pnl_percent": 0.0,
    "signal_confidence": 71.4,
    "reasons": [
      "๐ RSI (73.4) ูู ููุทูุฉ ุฐุฑูุฉ ุงูุดุฑุงุก - ูุฑุตุฉ ุจูุน",
      "๐ MACD ูุนุทู ุฅุดุงุฑุฉ ุตุงุนุฏุฉ",
      "๐ ุงูููุณุชูุฌุฑุงู ููุฌุจ - ุชุฃููุฏ ููุงุชุฌุงู ุงูุตุงุนุฏ",
      "๐ ุงููุชูุณุทุงุช ุงููุชุญุฑูุฉ ุชุดูุฑ ูุงุชุฌุงู ุตุงุนุฏ ููู",
      "๐ ุงูุณุนุฑ ููู ุงููุชูุณุทุงุช ุงููุชุญุฑูุฉ 20 ู 50"
    ]
  },
  {
    "id": "T00009",
    "ticker": "HRHO.CA",
    "company_name": "EFG Holding",
    "arabic_name": "ุฅู ุฅู ุฌู ุงููุงุจุถุฉ",
    "direction": "BUY",
    "entry_price": 29.62,
    "current_price": 29.62,
    "stop_loss": 28.14,
    "take_profit": 32.58,
    "quantity": 33,
    "investment_amount": 977.46,
    "entry_time": "2026-02-08T00:55:02.005060",
    "exit_time": null,
    "exit_price": null,
    "status": "ููุชูุญุฉ",
    "pnl": 0.0,
    "pnl_percent": 0.0,
    "signal_confidence": 71.4,
    "reasons": [
      "๐ RSI (70.0) ูู ููุทูุฉ ุฐุฑูุฉ ุงูุดุฑุงุก - ูุฑุตุฉ ุจูุน",
      "๐ MACD ูุนุทู ุฅุดุงุฑุฉ ุตุงุนุฏุฉ",
      "๐ ุงูููุณุชูุฌุฑุงู ููุฌุจ - ุชุฃููุฏ ููุงุชุฌุงู ุงูุตุงุนุฏ",
      "๐ ุงููุชูุณุทุงุช ุงููุชุญุฑูุฉ ุชุดูุฑ ูุงุชุฌุงู ุตุงุนุฏ ููู",
      "๐ ุงูุณุนุฑ ููู ุงููุชูุณุทุงุช ุงููุชุญุฑูุฉ 20 ู 50"
    ]
  },
  {
    "id": "T00010",
    "ticker": "ETEL.CA",
    "company_name": "Telecom Egypt",
    "arabic_name": "ุงููุตุฑูุฉ ููุงุชุตุงูุงุช",
    "direction": "BUY",
    "entry_price": 84.89,
    "current_price": 84.89,
    "stop_loss": 80.65,
    "take_profit": 93.38,
    "quantity": 11,
    "investment_amount": 933.79,
    "entry_time": "2026-02-08T00:55:02.030973",
    "exit_time": null,
    "exit_price": null,
    "status": "ููุชูุญุฉ",
    "pnl": 0.0,
    "pnl_percent": 0.0,
    "signal_confidence": 71.4,
    "reasons": [
      "๐ RSI (74.5) ูู ููุทูุฉ ุฐุฑูุฉ ุงูุดุฑุงุก - ูุฑุตุฉ ุจูุน",
      "๐ MACD ูุนุทู ุฅุดุงุฑุฉ ุตุงุนุฏุฉ",
      "๐ ุงูููุณุชูุฌุฑุงู ููุฌุจ - ุชุฃููุฏ ููุงุชุฌุงู ุงูุตุงุนุฏ",
      "๐ ุงููุชูุณุทุงุช ุงููุชุญุฑูุฉ ุชุดูุฑ ูุงุชุฌุงู ุตุงุนุฏ ููู",
      "๐ ุงูุณุนุฑ ููู ุงููุชูุณุทุงุช ุงููุชุญุฑูุฉ 20 ู 50"
    ]
  },
  {
    "id": "T00011",
    "ticker": "ABUK.CA",
    "company_name": "Abu Qir Fertilizers",
    "arabic_name": "ุฃุจูููุฑ ููุฃุณูุฏุฉ",
    "direction": "BUY",
    "entry_price": 65.66,
    "current_price": 65.66,
    "stop_loss": 62.38,
    "take_profit": 72.23,
    "quantity": 15,
    "investment_amount": 984.9,
    "entry_time": "2026-02-08T00:55:02.051225",
    "exit_time": null,
    "exit_price": null,
    "status": "ููุชูุญุฉ",
    "pnl": 0.0,
    "pnl_percent": 0.0,
    "signal_confidence": 71.4,
    "reasons": [
      "๐ RSI (78.2) ูู ููุทูุฉ ุฐุฑูุฉ ุงูุดุฑุงุก - ูุฑุตุฉ ุจูุน",
      "๐ MACD ูุนุทู ุฅุดุงุฑุฉ ุตุงุนุฏุฉ",
      "๐ ุงูููุณุชูุฌุฑุงู ููุฌุจ - ุชุฃููุฏ ููุงุชุฌุงู ุงูุตุงุนุฏ",
      "๐ ุงููุชูุณุทุงุช ุงููุชุญุฑูุฉ ุชุดูุฑ ูุงุชุฌุงู ุตุงุนุฏ ููู",
      "๐ ุงูุณุนุฑ ููู ุงููุชูุณุทุงุช ุงููุชุญุฑูุฉ 20 ู 50"
    ]
  },
  {
    "id": "T00012",
    "ticker": "EMFD.CA",
    "company_name": "Emaar Misr",
    "arabic_name": "ุฅุนูุงุฑ ูุตุฑ",
    "direction": "BUY",
    "entry_price": 9.4,
    "current_price": 9.4,
    "stop_loss": 8.93,
    "take_profit": 10.34,
    "quantity": 106,
    "investment_amount": 996.4,
    "entry_time": "2026-02-08T00:55:02.077125",
    "exit_time": null,
    "exit_price": null,
    "status": "ููุชูุญุฉ",
    "pnl": 0.0,
    "pnl_percent": 0.0,
    "signal_confidence": 70.0,
    "reasons": [
      "๐ MACD ูุนุทู ุฅุดุงุฑุฉ ุตุงุนุฏุฉ",
      "๐ ุงูููุณุชูุฌุฑุงู ููุฌุจ - ุชุฃููุฏ ููุงุชุฌุงู ุงูุตุงุนุฏ",
      "๐ ุงููุชูุณุทุงุช ุงููุชุญุฑูุฉ ุชุดูุฑ ูุงุชุฌุงู ูุงุจุท ููู",
      "๐ ุงูุณุนุฑ ููู ุงููุชูุณุทุงุช ุงููุชุญุฑูุฉ 20 ู 50"
    ]
  },
  {
    "id": "T00013",
    "ticker": "SKPC.CA",
    "company_name": "Sidi Kerir Petrochemicals",
    "arabic_name": "ุณูุฏู ูุฑูุฑ ููุจุชุฑููููุงููุงุช",
    "direction": "BUY",
    "entry_price": 15.2,
    "current_price": 15.2,
    "stop_loss": 14.44,
    "take_profit": 16.72,
    "quantity": 65,
    "investment_amount": 988.0,
    "entry_time": "2026-02-08T00:55:02.090440",
    "exit_time": null,
    "exit_price": null,
    "status": "ููุชูุญุฉ",
    "pnl": 0.0,
    "pnl_percent": 0.0,
    "signal_confidence": 70.0,
    "reasons": [
      "๐ RSI (38.0) ูููู ููุงูุฎูุงุถ",
      "๐ MACD ูุนุทู ุฅุดุงุฑุฉ ุตุงุนุฏุฉ",
      "๐ ุงูููุณุชูุฌุฑุงู ููุฌุจ - ุชุฃููุฏ ููุงุชุฌุงู ุงูุตุงุนุฏ",
      "๐ ุงููุชูุณุทุงุช ุงููุชุญุฑูุฉ ุชุดูุฑ ูุงุชุฌุงู ูุงุจุท ููู"
    ]
  },
  {
    "id": "T00014",
    "ticker": "ORWE.CA",
    "company_name": "Oriental Weavers",
    "arabic_name": "ุงูุณุฌุงุฏ ุงูุดุฑููุฉ",
    "direction": "BUY",
    "entry_price": 23.25,
    "current_price": 23.25,
    "stop_loss": 22.09,
    "take_profit": 25.58,
    "quantity": 43,
    "investment_amount": 999.75,
    "entry_time": "2026-02-08T00:55:02.118616",
    "exit_time": null,
    "exit_price": null,
    "status": "ููุชูุญุฉ",
    "pnl": 0.0,
    "pnl_percent": 0.0,
    "signal_confidence": 66.7,
    "reasons": [
      "๐ RSI (60.8) ูููู ููุงุฑุชูุงุน",
      "๐ MACD ูุนุทู ุฅุดุงุฑุฉ ุตุงุนุฏุฉ",
      "๐ ุงูููุณุชูุฌุฑุงู ููุฌุจ - ุชุฃููุฏ ููุงุชุฌุงู ุงูุตุงุนุฏ",
      "๐ ุงููุชูุณุทุงุช ุงููุชุญุฑูุฉ ุชุดูุฑ ูุงุชุฌุงู ูุงุจุท ููู",
      "๐ ุงูุณุนุฑ ููู ุงููุชูุณุทุงุช ุงููุชุญุฑูุฉ 20 ู 50",
      "๐ ุญุฌู ุชุฏุงูู ูุฑุชูุน (1.9x) - ุชุฃููุฏ ููุดุฑุงุก"
    ]
  }
]